[
  {
    "id": 1784069675819,
    "title": "⚠️ 중요 날씨 알림",
    "body": "23°C (22-32°C), 강수확률 30%, 흐림\n\n📋 발송 이유: 강수량 급감: 26mm → 0.5mm/h\n🕐 확인 시간: 2026. 7. 15. 오전 7:54:35",
    "type": "weather_change",
    "executionId": "github-actions-29374477570-2361",
    "timestamp": "2026-07-14T22:54:35.819Z",
    "source": "server"
  },
  {
    "id": 1784032829683,
    "title": "🚨 긴급 날씨 알림",
    "body": "26°C (22-32°C), 강수확률 10%, 구름많음\n\n📋 발송 이유: 집중호우 (26mm/h)\n🕐 확인 시간: 2026. 7. 14. 오후 9:40:29",
    "type": "weather_change",
    "executionId": "github-actions-29333358884-2360",
    "timestamp": "2026-07-14T12:40:29.683Z",
    "source": "server"
  },
  {
    "id": 1784028223604,
    "title": "⚠️ 중요 날씨 알림",
    "body": "26°C (22-32°C), 강수확률 10%, 구름많음\n\n📋 발송 이유: 강수량 급증: 0mm → 3mm/h\n🕐 확인 시간: 2026. 7. 14. 오후 8:23:43",
    "type": "weather_change",
    "executionId": "github-actions-29328721956-2359",
    "timestamp": "2026-07-14T11:23:43.604Z",
    "source": "server"
  },
  {
    "id": 1784023882106,
    "title": "🌆 저녁 브리핑",
    "body": "🌆 저녁 브리핑입니다.\n\n📅 내일의 일정:\n• 수요영화제 위대한개츠비\n\n⭐ HIGH 우선순위 작업:\n• 여권, 토익\n• 공통수학1, 2\n• 운전면허\n• 문학 데이터 분석 실습\n• 인공지능과 언어학\n• 찐영어\n• CLRS\n• 파이토치 교과서\n• 수1,수2,미적\n• 기하, 확통\n• 코테 책\n• 영어공부\n\n🔄 Daily 작업:\n• 영어 작문\n• 운동",
    "type": "evening_briefing",
    "executionId": "github-actions-29324416252-2358",
    "timestamp": "2026-07-14T10:11:22.106Z",
    "source": "server"
  },
  {
    "id": 1783850571437,
    "title": "🌆 저녁 브리핑",
    "body": "🌆 저녁 브리핑입니다.\n\n📅 내일의 일정:\n• 서울역 강수아\n• 무료토익…\n• 동건 20시?\n• 창업 해커톤 신청\n\n⭐ HIGH 우선순위 작업:\n• 여권, 토익\n• 공통수학1, 2\n• 운전면허\n• 문학 데이터 분석 실습\n• 인공지능과 언어학\n• 찐영어\n• CLRS\n• 파이토치 교과서\n• 수1,수2,미적\n• 기하, 확통\n• 코테 책\n• 영어공부\n\n🔄 Daily 작업:\n• 영어 작문\n• 운동",
    "type": "evening_briefing",
    "executionId": "github-actions-29188415597-2346",
    "timestamp": "2026-07-12T10:02:51.437Z",
    "source": "server"
  },
  {
    "id": 1783834706596,
    "title": "⚠️ 중요 날씨 알림",
    "body": "28°C (24-32°C), 강수확률 10%, 구름많음\n\n📋 발송 이유: 강수확률 급감: 60% → 10%\n🕐 확인 시간: 2026. 7. 12. 오후 2:38:26",
    "type": "weather_change",
    "executionId": "github-actions-29181456494-2345",
    "timestamp": "2026-07-12T05:38:26.596Z",
    "source": "server"
  },
  {
    "id": 1783809812019,
    "title": "🌤️ 날씨 변화 알림",
    "body": "24°C (24-34°C), 강수확률 60%, 흐림\n\n📋 발송 이유: 강수확률 변화: 30% → 60%\n🕐 확인 시간: 2026. 7. 12. 오전 7:43:31",
    "type": "weather_change",
    "executionId": "github-actions-29170974279-2343",
    "timestamp": "2026-07-11T22:43:32.019Z",
    "source": "server"
  },
  {
    "id": 1783771578098,
    "title": "🌤️ 날씨 변화 알림",
    "body": "24°C (24-34°C), 강수확률 30%, 흐림\n\n📋 발송 이유: 강수확률 변화: 60% → 30%\n🕐 확인 시간: 2026. 7. 11. 오후 9:06:17",
    "type": "weather_change",
    "executionId": "github-actions-29152066884-2342",
    "timestamp": "2026-07-11T12:06:18.098Z",
    "source": "server"
  },
  {
    "id": 1783763340897,
    "title": "🌤️ 날씨 변화 알림",
    "body": "26°C (24-34°C), 강수확률 60%, 흐림\n\n📋 발송 이유: 강수확률 변화: 30% → 60%\n🕐 확인 시간: 2026. 7. 11. 오후 6:49:00",
    "type": "weather_change",
    "executionId": "github-actions-29148327903-2340",
    "timestamp": "2026-07-11T09:49:00.897Z",
    "source": "server"
  },
  {
    "id": 1783638477267,
    "title": "🌤️ 날씨 변화 알림",
    "body": "29°C (24-33°C), 강수확률 30%, 흐림\n\n📋 발송 이유: 강수확률 변화: 0% → 30%\n🕐 확인 시간: 2026. 7. 10. 오전 8:07:56",
    "type": "weather_change",
    "executionId": "github-actions-29056517123-2332",
    "timestamp": "2026-07-09T23:07:57.267Z",
    "source": "server"
  },
  {
    "id": 1783595963731,
    "title": "🌤️ 날씨 변화 알림",
    "body": "27°C (23-33°C), 맑음\n\n📋 발송 이유: 강수확률 변화: 30% → 0%\n🕐 확인 시간: 2026. 7. 9. 오후 8:19:23",
    "type": "weather_change",
    "executionId": "github-actions-29014452774-2330",
    "timestamp": "2026-07-09T11:19:23.731Z",
    "source": "server"
  },
  {
    "id": 1783465081634,
    "title": "⚠️ 중요 날씨 알림",
    "body": "25°C (23-32°C), 강수확률 30%, 흐림\n\n📋 발송 이유: 강수 형태 변화: 없음 → 비\n🕐 확인 시간: 2026. 7. 8. 오전 7:58:01",
    "type": "weather_change",
    "executionId": "github-actions-28904485806-2321",
    "timestamp": "2026-07-07T22:58:01.634Z",
    "source": "server"
  },
  {
    "id": 1783379009033,
    "title": "⚠️ 중요 날씨 알림",
    "body": "26°C (24-31°C), 강수확률 30%, 흐림\n\n📋 발송 이유: 강수 형태 변화: 없음 → 비\n🕐 확인 시간: 2026. 7. 7. 오전 8:03:28",
    "type": "weather_change",
    "executionId": "github-actions-28829224328-2316",
    "timestamp": "2026-07-06T23:03:29.033Z",
    "source": "server"
  },
  {
    "id": 1783340126594,
    "title": "⚠️ 중요 날씨 알림",
    "body": "25°C (23-30°C), 강수확률 10%, 구름많음\n\n📋 발송 이유: 강수확률 급감: 60% → 10%\n🕐 확인 시간: 2026. 7. 6. 오후 9:15:26",
    "type": "weather_change",
    "executionId": "github-actions-28790654651-2314",
    "timestamp": "2026-07-06T12:15:26.594Z",
    "source": "server"
  },
  {
    "id": 1783320466350,
    "title": "⚠️ 중요 날씨 알림",
    "body": "27°C (23-30°C), 강수확률 60%, 흐림\n\n📋 발송 이유: 강수량 급감: 21.5mm → 0mm/h\n🕐 확인 시간: 2026. 7. 6. 오후 3:47:46",
    "type": "weather_change",
    "executionId": "github-actions-28773188660-2313",
    "timestamp": "2026-07-06T06:47:46.350Z",
    "source": "server"
  },
  {
    "id": 1783296981696,
    "title": "🚨 긴급 날씨 알림",
    "body": "25°C (23-30°C), 강수확률 60%, 흐림\n\n📋 발송 이유: 집중호우 (21.5mm/h)\n🕐 확인 시간: 2026. 7. 6. 오전 9:16:21",
    "type": "weather_change",
    "executionId": "github-actions-28759907967-2312",
    "timestamp": "2026-07-06T00:16:21.696Z",
    "source": "server"
  },
  {
    "id": 1783247288458,
    "title": "🌆 저녁 브리핑",
    "body": "🌆 저녁 브리핑입니다.\n\n📅 내일 등록된 일정이 없습니다.\n\n⭐ HIGH 우선순위 작업:\n• 여권, 토익\n• 공통수학1, 2\n• 운전면허\n• 문학 데이터 분석 실습\n• 인공지능과 언어학\n• 찐영어\n• CLRS\n• 파이토치 교과서\n• 수1,수2,미적\n• 기하, 확통\n• 코테 책\n• 영어공부\n\n🔄 Daily 작업:\n• 영어 작문\n• 운동",
    "type": "evening_briefing",
    "executionId": "github-actions-28737717604-2308",
    "timestamp": "2026-07-05T10:28:08.458Z",
    "source": "server"
  },
  {
    "id": 1783232106404,
    "title": "🌤️ 날씨 변화 알림",
    "body": "27°C (23-29°C), 강수확률 60%, 흐림\n\n📋 발송 이유: 강수확률 변화: 30% → 60%\n🕐 확인 시간: 2026. 7. 5. 오후 3:15:06",
    "type": "weather_change",
    "executionId": "github-actions-28731699443-2307",
    "timestamp": "2026-07-05T06:15:06.404Z",
    "source": "server"
  },
  {
    "id": 1783205711564,
    "title": "🌤️ 날씨 변화 알림",
    "body": "24°C (23-30°C), 강수확률 30%, 흐림\n\n📋 발송 이유: 강수확률 변화: 60% → 30%\n🕐 확인 시간: 2026. 7. 5. 오전 7:55:11",
    "type": "weather_change",
    "executionId": "github-actions-28722296139-2305",
    "timestamp": "2026-07-04T22:55:11.564Z",
    "source": "server"
  },
  {
    "id": 1783160746798,
    "title": "🌆 저녁 브리핑",
    "body": "🌆 저녁 브리핑입니다.\n\n📅 내일 등록된 일정이 없습니다.\n\n⭐ HIGH 우선순위 작업:\n• 여권, 토익\n• 공통수학1, 2\n• 운전면허\n• 문학 데이터 분석 실습\n• 인공지능과 언어학\n• 찐영어\n• CLRS\n• 파이토치 교과서\n• 수1,수2,미적\n• 기하, 확통\n• 코테 책\n• 영어공부\n\n🔄 Daily 작업:\n• 영어 작문\n• 운동",
    "type": "evening_briefing",
    "executionId": "github-actions-28703268631-2302",
    "timestamp": "2026-07-04T10:25:46.798Z",
    "source": "server"
  },
  {
    "id": 1782994040440,
    "title": "🌤️ 날씨 변화 알림",
    "body": "25°C (22-31°C), 강수확률 60%, 흐림\n\n📋 발송 이유: 강수확률 변화: 30% → 60%\n🕐 확인 시간: 2026. 7. 2. 오후 9:07:20",
    "type": "weather_change",
    "executionId": "github-actions-28588717609-2291",
    "timestamp": "2026-07-02T12:07:20.440Z",
    "source": "server"
  },
  {
    "id": 1782972604426,
    "title": "⚠️ 중요 날씨 알림",
    "body": "29°C (21-31°C), 강수확률 30%, 흐림\n\n📋 발송 이유: 강수 형태 변화: 없음 → 비\n🕐 확인 시간: 2026. 7. 2. 오후 3:10:04",
    "type": "weather_change",
    "executionId": "github-actions-28569374080-2289",
    "timestamp": "2026-07-02T06:10:04.426Z",
    "source": "server"
  },
  {
    "id": 1782905571317,
    "title": "🌤️ 날씨 변화 알림",
    "body": "24°C (21-30°C), 강수확률 30%, 흐림\n\n📋 발송 이유: 강수확률 변화: 0% → 30%\n🕐 확인 시간: 2026. 7. 1. 오후 8:32:51",
    "type": "weather_change",
    "executionId": "github-actions-28514435303-2285",
    "timestamp": "2026-07-01T11:32:51.317Z",
    "source": "server"
  },
  {
    "id": 1782687545054,
    "title": "🌤️ 날씨 변화 알림",
    "body": "22°C (21-31°C), 강수확률 30%, 흐림\n\n📋 발송 이유: 강수확률 변화: 0% → 30%\n🕐 확인 시간: 2026. 6. 29. 오전 7:59:04",
    "type": "weather_change",
    "executionId": "github-actions-28338894289-2272",
    "timestamp": "2026-06-28T22:59:05.054Z",
    "source": "server"
  },
  {
    "id": 1782555831388,
    "title": "🌆 저녁 브리핑",
    "body": "🌆 저녁 브리핑입니다.\n\n📅 내일 등록된 일정이 없습니다.\n\n⭐ HIGH 우선순위 작업:\n• 여권, 토익\n• 공통수학1, 2\n• 운전면허\n• 문학 데이터 분석 실습\n• 인공지능과 언어학\n• 찐영어\n• CLRS\n• 파이토치 교과서\n• 수1,수2,미적\n• 기하, 확통\n• 코테 책\n• 영어공부\n\n🔄 Daily 작업:\n• 영어 작문\n• 운동",
    "type": "evening_briefing",
    "executionId": "github-actions-28286431645-2263",
    "timestamp": "2026-06-27T10:23:51.388Z",
    "source": "server"
  },
  {
    "id": 1781909596953,
    "title": "⚠️ 중요 날씨 알림",
    "body": "19°C (18-29°C), 맑음\n\n📋 발송 이유: 강수 형태 변화: 없음 → 비\n🕐 확인 시간: 2026. 6. 20. 오전 7:53:16",
    "type": "weather_change",
    "executionId": "github-actions-27852003503-2222",
    "timestamp": "2026-06-19T22:53:16.953Z",
    "source": "server"
  },
  {
    "id": 1781871463269,
    "title": "🌤️ 날씨 변화 알림",
    "body": "23°C (18-29°C), 맑음\n\n📋 발송 이유: 강수확률 변화: 30% → 0%\n🕐 확인 시간: 2026. 6. 19. 오후 9:17:42",
    "type": "weather_change",
    "executionId": "github-actions-27825199130-2220",
    "timestamp": "2026-06-19T12:17:43.269Z",
    "source": "server"
  },
  {
    "id": 1781854168908,
    "title": "⚠️ 중요 날씨 알림",
    "body": "28°C (19-28°C), 강수확률 30%, 흐림\n\n📋 발송 이유: 강수 형태 변화: 없음 → 비\n🕐 확인 시간: 2026. 6. 19. 오후 4:29:28",
    "type": "weather_change",
    "executionId": "github-actions-27811972512-2219",
    "timestamp": "2026-06-19T07:29:28.908Z",
    "source": "server"
  },
  {
    "id": 1781652098980,
    "title": "🌤️ 날씨 변화 알림",
    "body": "24°C (20-32°C), 강수확률 30%, 흐림\n\n📋 발송 이유: 강수확률 변화: 0% → 30%\n🕐 확인 시간: 2026. 6. 17. 오전 8:21:38",
    "type": "weather_change",
    "executionId": "github-actions-27654674310-2207",
    "timestamp": "2026-06-16T23:21:38.980Z",
    "source": "server"
  },
  {
    "id": 1781615029994,
    "title": "🌤️ 날씨 변화 알림",
    "body": "23°C (20-32°C), 맑음\n\n📋 발송 이유: 강수확률 변화: 30% → 0%\n🕐 확인 시간: 2026. 6. 16. 오후 10:03:49",
    "type": "weather_change",
    "executionId": "github-actions-27619516300-2205",
    "timestamp": "2026-06-16T13:03:49.994Z",
    "source": "server"
  },
  {
    "id": 1781534088138,
    "title": "🚨 긴급 날씨 알림",
    "body": "22°C (20-32°C), 강수확률 30%, 흐림\n\n📋 발송 이유: 극단적 기온 변화: 30°C → 19°C\n🕐 확인 시간: 2026. 6. 15. 오후 11:34:47",
    "type": "weather_change",
    "executionId": "github-actions-27553769206-2200",
    "timestamp": "2026-06-15T14:34:48.138Z",
    "source": "server"
  },
  {
    "id": 1780741337282,
    "title": "🌆 저녁 브리핑",
    "body": "🌆 저녁 브리핑입니다.\n\n📅 내일의 일정:\n• 우진 13-15시\n• 우현 10-12시\n• 컴개 과제\n\n⭐ HIGH 우선순위 작업:\n• 여권, 토익\n• 공통수학1, 2\n• 운전면허\n• 문학 데이터 분석 실습\n• 인공지능과 언어학\n• 찐영어\n• CLRS\n• 파이토치 교과서\n• 수1,수2,미적\n• 기하, 확통\n• 코테 책\n• 영어공부\n\n🔄 Daily 작업:\n• 영어 작문\n• 운동",
    "type": "evening_briefing",
    "executionId": "github-actions-27059716672-2151",
    "timestamp": "2026-06-06T10:22:17.282Z",
    "source": "server"
  },
  {
    "id": 1780356286755,
    "title": "🌤️ 날씨 변화 알림",
    "body": "22°C (18-32°C), 강수확률 30%, 흐림\n\n📋 발송 이유: 날씨 변화: 맑음 → 흐림\n🕐 확인 시간: 2026. 6. 2. 오전 8:24:46",
    "type": "weather_change",
    "executionId": "github-actions-26788223862-2128",
    "timestamp": "2026-06-01T23:24:46.755Z",
    "source": "server"
  },
  {
    "id": 1780223092750,
    "title": "🌆 저녁 브리핑",
    "body": "🌆 저녁 브리핑입니다.\n\n📅 내일의 일정:\n• 동건 7시-9시\n\n⭐ HIGH 우선순위 작업:\n• 여권, 토익\n• 공통수학1, 2\n• 운전면허\n• 문학 데이터 분석 실습\n• 인공지능과 언어학\n• 찐영어\n• CLRS\n• 파이토치 교과서\n• 수1,수2,미적\n• 기하, 확통\n• 코테 책\n• 영어공부\n\n🔄 Daily 작업:\n• 영어 작문\n• 운동",
    "type": "evening_briefing",
    "executionId": "github-actions-26710038095-2120",
    "timestamp": "2026-05-31T10:24:52.750Z",
    "source": "server"
  },
  {
    "id": 1780136291394,
    "title": "🌆 저녁 브리핑",
    "body": "🌆 저녁 브리핑입니다.\n\n📅 내일의 일정:\n• 컴구 과제4\n\n⭐ HIGH 우선순위 작업:\n• 여권, 토익\n• 공통수학1, 2\n• 운전면허\n• 문학 데이터 분석 실습\n• 인공지능과 언어학\n• 찐영어\n• CLRS\n• 파이토치 교과서\n• 수1,수2,미적\n• 기하, 확통\n• 코테 책\n• 영어공부\n\n🔄 Daily 작업:\n• 영어 작문\n• 운동",
    "type": "evening_briefing",
    "executionId": "github-actions-26681327599-2114",
    "timestamp": "2026-05-30T10:18:11.394Z",
    "source": "server"
  },
  {
    "id": 1780009953232,
    "title": "🌤️ 날씨 변화 알림",
    "body": "23°C (15-28°C), 강수확률 30%, 흐림\n\n📋 발송 이유: 강수확률 변화: 0% → 30%\n🕐 확인 시간: 2026. 5. 29. 오전 8:12:32",
    "type": "weather_change",
    "executionId": "github-actions-26607752548-2106",
    "timestamp": "2026-05-28T23:12:33.232Z",
    "source": "server"
  },
  {
    "id": 1779882556987,
    "title": "⚠️ 중요 날씨 알림",
    "body": "19°C (15-29°C), 맑음\n\n📋 발송 이유: 강수 형태 변화: 없음 → 비\n🕐 확인 시간: 2026. 5. 27. 오후 8:49:16",
    "type": "weather_change",
    "executionId": "github-actions-26509274982-2099",
    "timestamp": "2026-05-27T11:49:16.987Z",
    "source": "server"
  },
  {
    "id": 1779668030113,
    "title": "🌤️ 날씨 변화 알림",
    "body": "21°C (17-30°C), 맑음\n\n📋 발송 이유: 강수확률 변화: 30% → 0%\n🕐 확인 시간: 2026. 5. 25. 오전 9:13:49",
    "type": "weather_change",
    "executionId": "github-actions-26376724054-2088",
    "timestamp": "2026-05-25T00:13:50.113Z",
    "source": "server"
  },
  {
    "id": 1779663284538,
    "title": "🌤️ 날씨 변화 알림",
    "body": "18°C (17-30°C), 강수확률 30%, 흐림\n\n📋 발송 이유: 강수확률 변화: 0% → 30%\n🕐 확인 시간: 2026. 5. 25. 오전 7:54:44",
    "type": "weather_change",
    "executionId": "github-actions-26375053422-2087",
    "timestamp": "2026-05-24T22:54:44.538Z",
    "source": "server"
  },
  {
    "id": 1779617533052,
    "title": "🌆 저녁 브리핑",
    "body": "🌆 저녁 브리핑입니다.\n\n📅 내일의 일정:\n• 동건 시간 조정\n• 공기사 휴강\n• 공휴일\n• 피에타 공연\n\n⭐ HIGH 우선순위 작업:\n• 여권, 토익\n• 공통수학1, 2\n• 운전면허\n• 문학 데이터 분석 실습\n• 인공지능과 언어학\n• 찐영어\n• CLRS\n• 파이토치 교과서\n• 수1,수2,미적\n• 기하, 확통\n• 코테 책\n• 영어공부\n\n🔄 Daily 작업:\n• 영어 작문\n• 운동",
    "type": "evening_briefing",
    "executionId": "github-actions-26358449190-2084",
    "timestamp": "2026-05-24T10:12:13.052Z",
    "source": "server"
  },
  {
    "id": 1779538117619,
    "title": "⚠️ 중요 날씨 알림",
    "body": "21°C (15-29°C), 강수확률 10%, 구름많음\n\n📋 발송 이유: 강수확률 급감: 60% → 10%\n🕐 확인 시간: 2026. 5. 23. 오후 9:08:37",
    "type": "weather_change",
    "executionId": "github-actions-26332257422-2080",
    "timestamp": "2026-05-23T12:08:37.619Z",
    "source": "server"
  },
  {
    "id": 1779534532606,
    "title": "🌤️ 날씨 변화 알림",
    "body": "19°C (15-29°C), 강수확률 60%, 흐림\n\n📋 발송 이유: 강수확률 변화: 20% → 60%\n🕐 확인 시간: 2026. 5. 23. 오후 8:08:52",
    "type": "weather_change",
    "executionId": "github-actions-26331101228-2079",
    "timestamp": "2026-05-23T11:08:52.606Z",
    "source": "server"
  },
  {
    "id": 1779530684556,
    "title": "🌆 저녁 브리핑",
    "body": "🌆 저녁 브리핑입니다.\n\n📅 내일의 일정:\n• 우진 13-15시\n• 우현 10-12시\n\n⭐ HIGH 우선순위 작업:\n• 여권, 토익\n• 공통수학1, 2\n• 운전면허\n• 문학 데이터 분석 실습\n• 인공지능과 언어학\n• 찐영어\n• CLRS\n• 파이토치 교과서\n• 수1,수2,미적\n• 기하, 확통\n• 코테 책\n• 영어공부\n\n🔄 Daily 작업:\n• 영어 작문\n• 운동",
    "type": "evening_briefing",
    "executionId": "github-actions-26329919762-2078",
    "timestamp": "2026-05-23T10:04:44.556Z",
    "source": "server"
  },
  {
    "id": 1779490515299,
    "title": "🌤️ 날씨 변화 알림",
    "body": "20°C (15-29°C), 강수확률 20%, 구름많음\n\n📋 발송 이유: 강수확률 변화: 60% → 20%\n🕐 확인 시간: 2026. 5. 23. 오전 7:55:14",
    "type": "weather_change",
    "executionId": "github-actions-26315875703-2075",
    "timestamp": "2026-05-22T22:55:15.299Z",
    "source": "server"
  },
  {
    "id": 1779452165639,
    "title": "⚠️ 중요 날씨 알림",
    "body": "21°C (15-29°C), 강수확률 60%, 흐림\n\n📋 발송 이유: 강수확률 급증: 10% → 60%\n🕐 확인 시간: 2026. 5. 22. 오후 9:16:05",
    "type": "weather_change",
    "executionId": "github-actions-26287200962-2074",
    "timestamp": "2026-05-22T12:16:05.639Z",
    "source": "server"
  },
  {
    "id": 1779318549589,
    "title": "⚠️ 중요 날씨 알림",
    "body": "21°C (13-27°C), 맑음\n\n📋 발송 이유: 강수량 급감: 5.5mm → 0mm/h\n🕐 확인 시간: 2026. 5. 21. 오전 8:09:09",
    "type": "weather_change",
    "executionId": "github-actions-26195226767-2065",
    "timestamp": "2026-05-20T23:09:09.589Z",
    "source": "server"
  },
  {
    "id": 1779279728118,
    "title": "⚠️ 중요 날씨 알림",
    "body": "19°C (13-27°C), 맑음\n\n📋 발송 이유: 강수량 급감: 5.5mm → 5.5mm/h\n🕐 확인 시간: 2026. 5. 20. 오후 9:22:07",
    "type": "weather_change",
    "executionId": "github-actions-26162178166-2064",
    "timestamp": "2026-05-20T12:22:08.118Z",
    "source": "server"
  },
  {
    "id": 1779276041255,
    "title": "⚠️ 중요 날씨 알림",
    "body": "19°C (13-27°C), 맑음\n\n📋 발송 이유: 강수량 급증: 3.5mm → 5.5mm/h\n🕐 확인 시간: 2026. 5. 20. 오후 8:20:40",
    "type": "weather_change",
    "executionId": "github-actions-26159193714-2063",
    "timestamp": "2026-05-20T11:20:41.255Z",
    "source": "server"
  },
  {
    "id": 1779257973006,
    "title": "⚠️ 중요 날씨 알림",
    "body": "23°C (13-26°C), 맑음\n\n📋 발송 이유: 강수량 급증: 0.5mm → 3.5mm/h\n🕐 확인 시간: 2026. 5. 20. 오후 3:19:32",
    "type": "weather_change",
    "executionId": "github-actions-26145153516-2062",
    "timestamp": "2026-05-20T06:19:33.006Z",
    "source": "server"
  },
  {
    "id": 1779231588843,
    "title": "🌤️ 날씨 변화 알림",
    "body": "14°C (13-26°C), 강수확률 30%, 흐림\n\n📋 발송 이유: 강수확률 변화: 0% → 30%\n🕐 확인 시간: 2026. 5. 20. 오전 7:59:48",
    "type": "weather_change",
    "executionId": "github-actions-26130444881-2060",
    "timestamp": "2026-05-19T22:59:48.843Z",
    "source": "server"
  },
  {
    "id": 1779149902683,
    "title": "🌤️ 날씨 변화 알림",
    "body": "20°C (14-27°C), 강수확률 10%, 맑음\n\n📋 발송 이유: 날씨 변화: 흐림 → 맑음\n🕐 확인 시간: 2026. 5. 19. 오전 9:18:22",
    "type": "weather_change",
    "executionId": "github-actions-26068220485-2056",
    "timestamp": "2026-05-19T00:18:22.683Z",
    "source": "server"
  },
  {
    "id": 1779086012568,
    "title": "🌤️ 날씨 변화 알림",
    "body": "21°C (15-26°C), 강수확률 30%, 흐림\n\n📋 발송 이유: 강수확률 변화: 60% → 30%\n🕐 확인 시간: 2026. 5. 18. 오후 3:33:32",
    "type": "weather_change",
    "executionId": "github-actions-26017483415-2052",
    "timestamp": "2026-05-18T06:33:32.568Z",
    "source": "server"
  },
  {
    "id": 1779058231018,
    "title": "🌤️ 날씨 변화 알림",
    "body": "15°C (15-29°C), 강수확률 60%, 흐림\n\n📋 발송 이유: 강수확률 변화: 20% → 60%\n🕐 확인 시간: 2026. 5. 18. 오전 7:50:30",
    "type": "weather_change",
    "executionId": "github-actions-26005025479-2050",
    "timestamp": "2026-05-17T22:50:31.018Z",
    "source": "server"
  },
  {
    "id": 1779019558762,
    "title": "🌤️ 날씨 변화 알림",
    "body": "17°C (14-29°C), 강수확률 20%, 구름많음\n\n📋 발송 이유: 강수확률 변화: 60% → 20%\n🕐 확인 시간: 2026. 5. 17. 오후 9:05:58",
    "type": "weather_change",
    "executionId": "github-actions-25990362139-2049",
    "timestamp": "2026-05-17T12:05:58.762Z",
    "source": "server"
  },
  {
    "id": 1779011976904,
    "title": "🌤️ 날씨 변화 알림",
    "body": "19°C (14-29°C), 강수확률 60%, 흐림\n\n📋 발송 이유: 강수확률 변화: 30% → 60%\n🕐 확인 시간: 2026. 5. 17. 오후 6:59:36",
    "type": "weather_change",
    "executionId": "github-actions-25987735566-2047",
    "timestamp": "2026-05-17T09:59:36.904Z",
    "source": "server"
  },
  {
    "id": 1778971260190,
    "title": "🌤️ 날씨 변화 알림",
    "body": "18°C (14-29°C), 강수확률 30%, 흐림\n\n📋 발송 이유: 강수확률 변화: 60% → 30%\n🕐 확인 시간: 2026. 5. 17. 오전 7:40:59",
    "type": "weather_change",
    "executionId": "github-actions-25974877407-2044",
    "timestamp": "2026-05-16T22:41:00.190Z",
    "source": "server"
  },
  {
    "id": 1778933231438,
    "title": "🌤️ 날씨 변화 알림",
    "body": "18°C (14-29°C), 강수확률 60%, 흐림\n\n📋 발송 이유: 강수확률 변화: 30% → 60%\n🕐 확인 시간: 2026. 5. 16. 오후 9:07:11",
    "type": "weather_change",
    "executionId": "github-actions-25961514565-2043",
    "timestamp": "2026-05-16T12:07:11.438Z",
    "source": "server"
  },
  {
    "id": 1778319847543,
    "title": "🌤️ 날씨 변화 알림",
    "body": "17°C (9-23°C), 강수확률 20%, 구름많음\n\n📋 발송 이유: 강수확률 변화: 60% → 20%\n🕐 확인 시간: 2026. 5. 9. 오후 6:44:07",
    "type": "weather_change",
    "executionId": "github-actions-25597995350-2000",
    "timestamp": "2026-05-09T09:44:07.543Z",
    "source": "server"
  },
  {
    "id": 1778280801745,
    "title": "🌤️ 날씨 변화 알림",
    "body": "14°C (9-23°C), 강수확률 60%, 흐림\n\n📋 발송 이유: 강수확률 변화: 20% → 60%\n🕐 확인 시간: 2026. 5. 9. 오전 7:53:21",
    "type": "weather_change",
    "executionId": "github-actions-25583451347-1997",
    "timestamp": "2026-05-08T22:53:21.745Z",
    "source": "server"
  },
  {
    "id": 1778238713136,
    "title": "🌤️ 날씨 변화 알림",
    "body": "16°C (9-23°C), 강수확률 20%, 구름많음\n\n📋 발송 이유: 강수확률 변화: 60% → 20%\n🕐 확인 시간: 2026. 5. 8. 오후 8:11:52",
    "type": "weather_change",
    "executionId": "github-actions-25552397955-1995",
    "timestamp": "2026-05-08T11:11:53.136Z",
    "source": "server"
  },
  {
    "id": 1778217101687,
    "title": "🌤️ 날씨 변화 알림",
    "body": "21°C (9-23°C), 강수확률 60%, 흐림\n\n📋 발송 이유: 강수확률 변화: 30% → 60%\n🕐 확인 시간: 2026. 5. 8. 오후 2:11:41",
    "type": "weather_change",
    "executionId": "github-actions-25538087615-1992",
    "timestamp": "2026-05-08T05:11:41.687Z",
    "source": "server"
  },
  {
    "id": 1778063244173,
    "title": "🌆 저녁 브리핑",
    "body": "🌆 저녁 브리핑입니다.\n\n📅 내일 등록된 일정이 없습니다.\n\n⭐ HIGH 우선순위 작업:\n• 찐영어\n• 파이토치 교과서\n• 인공지능과 언어학\n• 문학 데이터 분석 실습\n• 기하, 확통\n• 영어공부\n• 코테 책\n• 수1,수2,미적\n• CLRS\n• 운전면허\n• 공통수학1, 2\n• 여권, 토익\n\n🔄 Daily 작업:\n• 운동\n• 영어 작문",
    "type": "evening_briefing",
    "executionId": "github-actions-25429871097-1981",
    "timestamp": "2026-05-06T10:27:24.173Z",
    "source": "server"
  },
  {
    "id": 1777975975155,
    "title": "🌆 저녁 브리핑",
    "body": "🌆 저녁 브리핑입니다.\n\n📅 내일의 일정:\n• 로컬창업 12-14시 온라인\n• 김정연 교수 특강 온라인 21시\n\n⭐ HIGH 우선순위 작업:\n• 찐영어\n• 파이토치 교과서\n• 인공지능과 언어학\n• 문학 데이터 분석 실습\n• 기하, 확통\n• 영어공부\n• 코테 책\n• 수1,수2,미적\n• CLRS\n• 운전면허\n• 공통수학1, 2\n• 여권, 토익\n\n🔄 Daily 작업:\n• 운동\n• 영어 작문",
    "type": "evening_briefing",
    "executionId": "github-actions-25370412651-1975",
    "timestamp": "2026-05-05T10:12:55.155Z",
    "source": "server"
  },
  {
    "id": 1777890335947,
    "title": "🌆 저녁 브리핑",
    "body": "🌆 저녁 브리핑입니다.\n\n📅 내일의 일정:\n• 운체 휴강 보강주 수업\n• 컴비 휴강\n\n⭐ HIGH 우선순위 작업:\n• 찐영어\n• 파이토치 교과서\n• 인공지능과 언어학\n• 문학 데이터 분석 실습\n• 기하, 확통\n• 영어공부\n• 코테 책\n• 수1,수2,미적\n• CLRS\n• 운전면허\n• 공통수학1, 2\n• 여권, 토익\n\n🔄 Daily 작업:\n• 운동\n• 영어 작문",
    "type": "evening_briefing",
    "executionId": "github-actions-25313842364-1969",
    "timestamp": "2026-05-04T10:25:35.947Z",
    "source": "server"
  },
  {
    "id": 1777761435963,
    "title": "⚠️ 중요 날씨 알림",
    "body": "11°C (8-22°C), 맑음\n\n📋 발송 이유: 강수 형태 변화: 없음 → 비\n🕐 확인 시간: 2026. 5. 3. 오전 7:37:15",
    "type": "weather_change",
    "executionId": "github-actions-25263615717-1960",
    "timestamp": "2026-05-02T22:37:15.963Z",
    "source": "server"
  },
  {
    "id": 1777548357625,
    "title": "🌤️ 날씨 변화 알림",
    "body": "12°C (9-23°C), 맑음\n\n📋 발송 이유: 강수확률 변화: 30% → 0%\n🕐 확인 시간: 2026. 4. 30. 오후 8:25:57",
    "type": "weather_change",
    "executionId": "github-actions-25162757908-1946",
    "timestamp": "2026-04-30T11:25:57.625Z",
    "source": "server"
  },
  {
    "id": 1777544373760,
    "title": "🌆 저녁 브리핑",
    "body": "🌆 저녁 브리핑입니다.\n\n📅 내일의 일정:\n• 매쓰랩 2회\n• 근로 없음\n\n⭐ HIGH 우선순위 작업:\n• 찐영어\n• 파이토치 교과서\n• 인공지능과 언어학\n• 문학 데이터 분석 실습\n• 기하, 확통\n• 영어공부\n• 코테 책\n• 수1,수2,미적\n• CLRS\n• 운전면허\n• 공통수학1, 2\n• 여권, 토익\n\n🔄 Daily 작업:\n• 운동\n• 영어 작문",
    "type": "evening_briefing",
    "executionId": "github-actions-25160121020-1945",
    "timestamp": "2026-04-30T10:19:33.760Z",
    "source": "server"
  },
  {
    "id": 1777527598708,
    "title": "🌤️ 날씨 변화 알림",
    "body": "18°C (10-22°C), 강수확률 30%, 흐림\n\n📋 발송 이유: 강수확률 변화: 60% → 30%\n🕐 확인 시간: 2026. 4. 30. 오후 2:39:58",
    "type": "weather_change",
    "executionId": "github-actions-25149386134-1944",
    "timestamp": "2026-04-30T05:39:58.708Z",
    "source": "server"
  },
  {
    "id": 1777503210148,
    "title": "🌤️ 날씨 변화 알림",
    "body": "12°C (10-22°C), 강수확률 60%, 흐림\n\n📋 발송 이유: 강수확률 변화: 20% → 60%\n🕐 확인 시간: 2026. 4. 30. 오전 7:53:29",
    "type": "weather_change",
    "executionId": "github-actions-25138036442-1942",
    "timestamp": "2026-04-29T22:53:30.148Z",
    "source": "server"
  },
  {
    "id": 1777457951664,
    "title": "🌆 저녁 브리핑",
    "body": "🌆 저녁 브리핑입니다.\n\n📅 내일의 일정:\n• 컴구 과제3\n• 근로 13-16시\n• 매쓰랩 1회\n• 부전공 취소\n\n⭐ HIGH 우선순위 작업:\n• 찐영어\n• 파이토치 교과서\n• 인공지능과 언어학\n• 문학 데이터 분석 실습\n• 기하, 확통\n• 영어공부\n• 코테 책\n• 수1,수2,미적\n• CLRS\n• 운전면허\n• 공통수학1, 2\n• 여권, 토익\n\n🔄 Daily 작업:\n• 운동\n• 영어 작문",
    "type": "evening_briefing",
    "executionId": "github-actions-25103366732-1939",
    "timestamp": "2026-04-29T10:19:11.664Z",
    "source": "server"
  },
  {
    "id": 1777376567836,
    "title": "🌤️ 날씨 변화 알림",
    "body": "14°C (7-21°C), 강수확률 30%, 흐림\n\n📋 발송 이유: 강수확률 변화: 0% → 30%\n🕐 확인 시간: 2026. 4. 28. 오후 8:42:47",
    "type": "weather_change",
    "executionId": "github-actions-25050771199-1934",
    "timestamp": "2026-04-28T11:42:47.836Z",
    "source": "server"
  },
  {
    "id": 1777371946432,
    "title": "🌆 저녁 브리핑",
    "body": "🌆 저녁 브리핑입니다.\n\n📅 내일의 일정:\n• 컴개 중간 6:45\n\n⭐ HIGH 우선순위 작업:\n• 찐영어\n• 파이토치 교과서\n• 인공지능과 언어학\n• 문학 데이터 분석 실습\n• 기하, 확통\n• 영어공부\n• 코테 책\n• 수1,수2,미적\n• CLRS\n• 운전면허\n• 공통수학1, 2\n• 여권, 토익\n\n🔄 Daily 작업:\n• 운동\n• 영어 작문",
    "type": "evening_briefing",
    "executionId": "github-actions-25047546750-1933",
    "timestamp": "2026-04-28T10:25:46.432Z",
    "source": "server"
  },
  {
    "id": 1777290180814,
    "title": "⚠️ 중요 날씨 알림",
    "body": "13°C (7-20°C), 강수확률 20%, 구름많음\n\n📋 발송 이유: 강수 형태 변화: 없음 → 비\n🕐 확인 시간: 2026. 4. 27. 오후 8:43:00",
    "type": "weather_change",
    "executionId": "github-actions-24992976999-1928",
    "timestamp": "2026-04-27T11:43:00.814Z",
    "source": "server"
  },
  {
    "id": 1777285612206,
    "title": "🌆 저녁 브리핑",
    "body": "🌆 저녁 브리핑입니다.\n\n📅 내일 등록된 일정이 없습니다.\n\n⭐ HIGH 우선순위 작업:\n• 찐영어\n• 파이토치 교과서\n• 인공지능과 언어학\n• 문학 데이터 분석 실습\n• 기하, 확통\n• 영어공부\n• 코테 책\n• 수1,수2,미적\n• CLRS\n• 운전면허\n• 공통수학1, 2\n• 여권, 토익\n\n🔄 Daily 작업:\n• 운동\n• 영어 작문",
    "type": "evening_briefing",
    "executionId": "github-actions-24989739164-1927",
    "timestamp": "2026-04-27T10:26:52.206Z",
    "source": "server"
  },
  {
    "id": 1777032424767,
    "title": "🌤️ 날씨 변화 알림",
    "body": "13°C (9-24°C), 강수확률 10%, 맑음\n\n📋 발송 이유: 날씨 변화: 흐림 → 맑음\n🕐 확인 시간: 2026. 4. 24. 오후 9:07:04",
    "type": "weather_change",
    "executionId": "github-actions-24888632136-1910",
    "timestamp": "2026-04-24T12:07:04.767Z",
    "source": "server"
  },
  {
    "id": 1777024514969,
    "title": "🌤️ 날씨 변화 알림",
    "body": "15°C (9-24°C), 강수확률 30%, 흐림\n\n📋 발송 이유: 강수확률 변화: 0% → 30%\n🕐 확인 시간: 2026. 4. 24. 오후 6:55:14",
    "type": "weather_change",
    "executionId": "github-actions-24883534599-1908",
    "timestamp": "2026-04-24T09:55:14.969Z",
    "source": "server"
  },
  {
    "id": 1776683846836,
    "title": "🌤️ 날씨 변화 알림",
    "body": "14°C (6-23°C), 맑음\n\n📋 발송 이유: 강수확률 변화: 30% → 0%\n🕐 확인 시간: 2026. 4. 20. 오후 8:17:26",
    "type": "weather_change",
    "executionId": "github-actions-24663541459-1882",
    "timestamp": "2026-04-20T11:17:26.836Z",
    "source": "server"
  },
  {
    "id": 1776679791884,
    "title": "🌆 저녁 브리핑",
    "body": "🌆 저녁 브리핑입니다.\n\n📅 내일의 일정:\n• 공소특 신청하기\n• 운체 중간 3시\n• 컴비 중간\n\n⭐ HIGH 우선순위 작업:\n• 찐영어\n• 파이토치 교과서\n• 인공지능과 언어학\n• 문학 데이터 분석 실습\n• 기하, 확통\n• 영어공부\n• 코테 책\n• 수1,수2,미적\n• CLRS\n• 운전면허\n• 공통수학1, 2\n• 여권, 토익\n\n🔄 Daily 작업:\n• 운동\n• 영어 작문",
    "type": "evening_briefing",
    "executionId": "github-actions-24660767163-1881",
    "timestamp": "2026-04-20T10:09:51.884Z",
    "source": "server"
  },
  {
    "id": 1776119986907,
    "title": "🌤️ 날씨 변화 알림",
    "body": "13°C (10-25°C), 강수확률 30%, 흐림\n\n📋 발송 이유: 강수확률 변화: 0% → 30%\n🕐 확인 시간: 2026. 4. 14. 오전 7:39:46",
    "type": "weather_change",
    "executionId": "github-actions-24370551635-1836",
    "timestamp": "2026-04-13T22:39:46.907Z",
    "source": "server"
  },
  {
    "id": 1776074749690,
    "title": "🌆 저녁 브리핑",
    "body": "🌆 저녁 브리핑입니다.\n\n📅 내일 등록된 일정이 없습니다.\n\n⭐ HIGH 우선순위 작업:\n• 찐영어\n• 파이토치 교과서\n• 인공지능과 언어학\n• 문학 데이터 분석 실습\n• 기하, 확통\n• 영어공부\n• 코테 책\n• 수1,수2,미적\n• CLRS\n• 운전면허\n• 공통수학1, 2\n• 여권, 토익\n\n🔄 Daily 작업:\n• 운동\n• 영어 작문",
    "type": "evening_briefing",
    "executionId": "github-actions-24337634049-1833",
    "timestamp": "2026-04-13T10:05:49.690Z",
    "source": "server"
  },
  {
    "id": 1775970438576,
    "title": "🚨 긴급 날씨 알림",
    "body": "22°C (7-24°C), 맑음\n\n📋 발송 이유: 극단적 기온 변화: 7°C → 20°C\n🕐 확인 시간: 2026. 4. 12. 오후 2:07:18",
    "type": "weather_change",
    "executionId": "github-actions-24299216878-1825",
    "timestamp": "2026-04-12T05:07:18.576Z",
    "source": "server"
  },
  {
    "id": 1775951460550,
    "title": "🌤️ 날씨 변화 알림",
    "body": "16°C (7-24°C), 강수확률 30%, 흐림\n\n📋 발송 이유: 강수확률 변화: 0% → 30%\n🕐 확인 시간: 2026. 4. 12. 오전 8:51:00",
    "type": "weather_change",
    "executionId": "github-actions-24294327647-1824",
    "timestamp": "2026-04-11T23:51:00.550Z",
    "source": "server"
  },
  {
    "id": 1775946501763,
    "title": "🌅 아침 브리핑",
    "body": "🌅 좋은 아침입니다!\n\n🌤️ 오늘 날씨: 12°C (7-24°C), 강수확률 30%, 흐림\n\n📅 오늘의 일정:\n• 운체 과제\n• 생동성\n\n⭐ HIGH 우선순위 작업:\n• 찐영어\n• 파이토치 교과서\n• 인공지능과 언어학\n• 문학 데이터 분석 실습\n• 기하, 확통\n• 영어공부\n• 코테 책\n• 수1,수2,미적\n• CLRS\n• 운전면허\n• 공통수학1, 2\n• 여권, 토익\n\n🔄 Daily 작업:\n• 운동\n• 영어 작문\n\n",
    "type": "morning_briefing",
    "executionId": "github-actions-24293018045-1823",
    "timestamp": "2026-04-11T22:28:21.763Z",
    "source": "server"
  },
  {
    "id": 1775865128316,
    "title": "🌤️ 날씨 변화 알림",
    "body": "16°C (5-24°C), 강수확률 10%, 맑음\n\n📋 발송 이유: 날씨 변화: 흐림 → 맑음\n🕐 확인 시간: 2026. 4. 11. 오전 8:52:08",
    "type": "weather_change",
    "executionId": "github-actions-24269428648-1817",
    "timestamp": "2026-04-10T23:52:08.316Z",
    "source": "server"
  },
  {
    "id": 1775709736031,
    "title": "⚠️ 중요 날씨 알림",
    "body": "19°C (6-21°C), 강수확률 20%, 구름많음\n\n📋 발송 이유: 강수량 급증: 0mm → 3mm/h\n🕐 확인 시간: 2026. 4. 9. 오후 1:42:15",
    "type": "weather_change",
    "executionId": "github-actions-24172779472-1804",
    "timestamp": "2026-04-09T04:42:16.031Z",
    "source": "server"
  },
  {
    "id": 1775519553896,
    "title": "🌤️ 날씨 변화 알림",
    "body": "11°C (3-16°C), 강수확률 20%, 구름많음\n\n📋 발송 이유: 강수확률 변화: 60% → 20%\n🕐 확인 시간: 2026. 4. 7. 오전 8:52:33",
    "type": "weather_change",
    "executionId": "github-actions-24057027610-1789",
    "timestamp": "2026-04-06T23:52:33.896Z",
    "source": "server"
  },
  {
    "id": 1775514785458,
    "title": "⚠️ 중요 날씨 알림",
    "body": "10°C (3-16°C), 강수확률 60%, 흐림\n\n📋 발송 이유: 강수확률 급증: 0% → 60%\n🕐 확인 시간: 2026. 4. 7. 오전 7:33:05",
    "type": "weather_change",
    "executionId": "github-actions-24054499410-1788",
    "timestamp": "2026-04-06T22:33:05.458Z",
    "source": "server"
  },
  {
    "id": 1775476739173,
    "title": "⚠️ 중요 날씨 알림",
    "body": "10°C (3-16°C), 맑음\n\n📋 발송 이유: 강수확률 급감: 60% → 0%\n🕐 확인 시간: 2026. 4. 6. 오후 8:58:58",
    "type": "weather_change",
    "executionId": "github-actions-24030929987-1787",
    "timestamp": "2026-04-06T11:58:59.173Z",
    "source": "server"
  },
  {
    "id": 1775451976637,
    "title": "🌤️ 날씨 변화 알림",
    "body": "11°C (3-14°C), 강수확률 60%, 흐림\n\n📋 발송 이유: 강수확률 변화: 30% → 60%\n🕐 확인 시간: 2026. 4. 6. 오후 2:06:16",
    "type": "weather_change",
    "executionId": "github-actions-24019524540-1783",
    "timestamp": "2026-04-06T05:06:16.637Z",
    "source": "server"
  },
  {
    "id": 1775432992392,
    "title": "🌤️ 날씨 변화 알림",
    "body": "10°C (3-14°C), 강수확률 30%, 흐림\n\n📋 발송 이유: 강수확률 변화: 0% → 30%\n🕐 확인 시간: 2026. 4. 6. 오전 8:49:51",
    "type": "weather_change",
    "executionId": "github-actions-24013207947-1782",
    "timestamp": "2026-04-05T23:49:52.392Z",
    "source": "server"
  },
  {
    "id": 1775428080704,
    "title": "🌅 아침 브리핑",
    "body": "🌅 좋은 아침입니다!\n\n🌤️ 오늘 날씨: 6°C (3-14°C), 강수확률 30%, 흐림\n\n📅 오늘의 일정:\n• 생동성 1기 퇴원\n• 동건 19.5-21.5시\n\n⭐ HIGH 우선순위 작업:\n• 찐영어\n• 파이토치 교과서\n• 인공지능과 언어학\n• 문학 데이터 분석 실습\n• 기하, 확통\n• 영어공부\n• 코테 책\n• 수1,수2,미적\n• CLRS\n• 운전면허\n• 공통수학1, 2\n• 여권, 토익\n\n🔄 Daily 작업:\n• 운동\n• 영어 작문\n\n",
    "type": "morning_briefing",
    "executionId": "github-actions-24011882385-1781",
    "timestamp": "2026-04-05T22:28:00.704Z",
    "source": "server"
  },
  {
    "id": 1775341555535,
    "title": "🌅 아침 브리핑",
    "body": "🌅 좋은 아침입니다!\n\n🌤️ 오늘 날씨: 3°C (2-15°C), 맑음\n\n📅 오늘의 일정:\n• 생동성\n\n⭐ HIGH 우선순위 작업:\n• 찐영어\n• 파이토치 교과서\n• 인공지능과 언어학\n• 문학 데이터 분석 실습\n• 기하, 확통\n• 영어공부\n• 코테 책\n• 수1,수2,미적\n• CLRS\n• 운전면허\n• 공통수학1, 2\n\n🔄 Daily 작업:\n• 운동\n• 영어 작문\n\n",
    "type": "morning_briefing",
    "executionId": "github-actions-23988878804-1774",
    "timestamp": "2026-04-04T22:25:55.535Z",
    "source": "server"
  },
  {
    "id": 1775255376080,
    "title": "🌅 아침 브리핑",
    "body": "🌅 좋은 아침입니다!\n\n🌤️ 오늘 날씨: 4°C (3-17°C), 맑음\n\n📅 오늘의 일정:\n• AI TOP 100 본선\n• 생동성 1기 입원 17시\n• 우진 13-15시\n• 우현 10-12시\n\n⭐ HIGH 우선순위 작업:\n• 찐영어\n• 파이토치 교과서\n• 인공지능과 언어학\n• 문학 데이터 분석 실습\n• 기하, 확통\n• 영어공부\n• 코테 책\n• 수1,수2,미적\n• CLRS\n• 운전면허\n• 공통수학1, 2\n\n🔄 Daily 작업:\n• 운동\n• 영어 작문\n\n",
    "type": "morning_briefing",
    "executionId": "github-actions-23964588948-1767",
    "timestamp": "2026-04-03T22:29:36.080Z",
    "source": "server"
  },
  {
    "id": 1775191148202,
    "title": "⚠️ 중요 날씨 알림",
    "body": "13°C (4-19°C), 강수확률 10%, 맑음\n\n📋 발송 이유: 강수확률 급감: 60% → 10%\n🕐 확인 시간: 2026. 4. 3. 오후 1:39:07",
    "type": "weather_change",
    "executionId": "github-actions-23934037821-1762",
    "timestamp": "2026-04-03T04:39:08.202Z",
    "source": "server"
  },
  {
    "id": 1775173850714,
    "title": "⚠️ 중요 날씨 알림",
    "body": "9°C (4-19°C), 강수확률 60%, 흐림\n\n📋 발송 이유: 강수확률 급증: 0% → 60%\n🕐 확인 시간: 2026. 4. 3. 오전 8:50:50",
    "type": "weather_change",
    "executionId": "github-actions-23927320340-1761",
    "timestamp": "2026-04-02T23:50:50.714Z",
    "source": "server"
  },
  {
    "id": 1775168909418,
    "title": "🌅 아침 브리핑",
    "body": "🌅 좋은 아침입니다!\n\n🌤️ 오늘 날씨: 7°C (4-19°C), 강수확률 60%, 흐림\n\n📅 오늘 등록된 일정이 없습니다.\n\n⭐ HIGH 우선순위 작업:\n• 찐영어\n• 파이토치 교과서\n• 인공지능과 언어학\n• 문학 데이터 분석 실습\n• 기하, 확통\n• 영어공부\n• 코테 책\n• 수1,수2,미적\n• CLRS\n• 운전면허\n• 공통수학1, 2\n\n🔄 Daily 작업:\n• 운동\n• 영어 작문\n\n",
    "type": "morning_briefing",
    "executionId": "github-actions-23924952115-1760",
    "timestamp": "2026-04-02T22:28:29.418Z",
    "source": "server"
  },
  {
    "id": 1775131127987,
    "title": "🌤️ 날씨 변화 알림",
    "body": "8°C (5-19°C), 맑음\n\n📋 발송 이유: 강수확률 변화: 30% → 0%\n🕐 확인 시간: 2026. 4. 2. 오후 8:58:47",
    "type": "weather_change",
    "executionId": "github-actions-23899254209-1759",
    "timestamp": "2026-04-02T11:58:47.987Z",
    "source": "server"
  },
  {
    "id": 1774823261851,
    "title": "🌅 아침 브리핑",
    "body": "🌅 좋은 아침입니다!\n\n🌤️ 오늘 날씨: 4°C (3-20°C), 맑음\n\n📅 오늘의 일정:\n• 동건 19.5-21.5시\n\n⭐ HIGH 우선순위 작업:\n• 찐영어\n• 파이토치 교과서\n• 인공지능과 언어학\n• 문학 데이터 분석 실습\n• 기하, 확통\n• 영어공부\n• 코테 책\n• 수1,수2,미적\n• CLRS\n• 운전면허\n• 공통수학1, 2\n\n🔄 Daily 작업:\n• 운동\n• 영어 작문\n\n",
    "type": "morning_briefing",
    "executionId": "github-actions-23720576791-1732",
    "timestamp": "2026-03-29T22:27:41.851Z",
    "source": "server"
  },
  {
    "id": 1774741605209,
    "title": "🌤️ 날씨 변화 알림",
    "body": "11°C (6-20°C), 강수확률 30%, 흐림\n\n📋 발송 이유: 강수확률 변화: 0% → 30%\n🕐 확인 시간: 2026. 3. 29. 오전 8:46:44",
    "type": "weather_change",
    "executionId": "github-actions-23697024102-1726",
    "timestamp": "2026-03-28T23:46:45.209Z",
    "source": "server"
  },
  {
    "id": 1774736758096,
    "title": "🌅 아침 브리핑",
    "body": "🌅 좋은 아침입니다!\n\n🌤️ 오늘 날씨: 7°C (6-20°C), 강수확률 20%, 구름많음\n\n📅 오늘의 일정:\n• 우진 13-15시\n• 우현 15회차\n\n⭐ HIGH 우선순위 작업:\n• 찐영어\n• 파이토치 교과서\n• 인공지능과 언어학\n• 문학 데이터 분석 실습\n• 기하, 확통\n• 영어공부\n• 코테 책\n• 수1,수2,미적\n• CLRS\n• 운전면허\n• 공통수학1, 2\n\n🔄 Daily 작업:\n• 운동\n• 영어 작문\n\n",
    "type": "morning_briefing",
    "executionId": "github-actions-23695689853-1725",
    "timestamp": "2026-03-28T22:25:58.096Z",
    "source": "server"
  }
]